{
    "FILENAME": "prueba 1_10",
    "REGISTRO": "d17996db-b31e-4105-99ea-3ff65cdae7e8",
    "FechaRegistro": "08/05/2021",
    "NIF": [
        "B47776067",
        "12164189H"
    ],
    "Email": [],
    "Telefono": [
        "983403130"
    ],
    "FechasExpedici\u00f3n": [
        "28/02/2020"
    ],
    "ListaPrecios": [
        96.0,
        1.83,
        175.68,
        10.0,
        158.11,
        30.0,
        2.85,
        85.5,
        10.0,
        76.95,
        168.0,
        2.5,
        420.0,
        10.0,
        378.0,
        120.0,
        2.66,
        319.2,
        10.0,
        287.28,
        90.0,
        3.65,
        328.5,
        10.0,
        295.65,
        24.0,
        19.15,
        459.6,
        10.0,
        413.64,
        180.0,
        3.71,
        667.8,
        10.0,
        601.02,
        270.0,
        3.28,
        885.6,
        10.0,
        797.04,
        120.0,
        3.56,
        427.2,
        10.0,
        384.48,
        3392.17,
        712.36,
        21.0,
        3392.17,
        4104.53
    ],
    "PrecioTotal": 4104.53,
    "BASE": 3392.17,
    "IVACANT": 712.36,
    "%IVA": 21.0
}